tfdocs/__init__.py
tfdocs/__main__.py
tfdocs/cli.py
tfdocs/db/__init__.py
tfdocs/db/args.py
tfdocs/db/handler.py
tfdocs/db/init.py
tfdocs/db/sync.py
tfdocs/db/tables.py
tfdocs/db/test_db_init.py
tfdocs/db/test_db_sync.py
tfdocs/db/test_handler.py
tfdocs/logging/__init__.py
tfdocs/logging/setup.py
tfdocs/logging/test_setup.py
tfdocs/logging/test_watch_logs.py
tfdocs/logging/watch_logs.py
tfdocs/models/attribute.py
tfdocs/models/block.py
tfdocs/models/blocks/datasource.py
tfdocs/models/blocks/provider.py
tfdocs/models/blocks/resource.py
tfdocs/models/blocks/test_datasource.py
tfdocs/models/blocks/test_provider.py
tfdocs/models/blocks/test_resource.py
tfdocs/models/default_providers.py
tfdocs/models/lazy_entity.py
tfdocs/models/test_attribute.py
tfdocs/models/test_block.py
tfdocs/models/test_lazy_entity.py
tfdocs/models/test_types.py
tfdocs/models/types.py
tfdocs/test_cli.py
tfdocs/test_main.py
tfdocs/test_utils.py
tfdocs/utils.py
tfdocs/views/app.py
tfdocs/views/component_viewer.py
tfdocs/views/layout.py
tfdocs/views/list.py
tfdocs/views/special.py
tfdocs/views/special_panes/help.py
tfdocs/views/special_panes/provider.py
tfdocs/views/special_panes/test_help.py
tfdocs/views/special_panes/test_provider_view.py
tfdocs/views/styles/component_viewer.tcss
tfdocs/views/styles/viewer.tcss
tfdocs/views/switcher.py
tfdocs/views/vertical.py
tfdocs/views/viewer.py
tfdocs_cli-0.2.24.dist-info/METADATA
tfdocs_cli-0.2.24.dist-info/WHEEL
tfdocs_cli-0.2.24.dist-info/entry_points.txt
tfdocs_cli-0.2.24.dist-info/RECORD
