Metadata-Version: 2.1
Name: tfdocs-cli
Version: 0.2.24
Summary: Terraform provider documentation viewer for the CLI
Author: acrease
Author-email: alex@crease.sh
Requires-Python: >=3.11,<3.14
Classifier: Programming Language :: Python :: 3
Classifier: Programming Language :: Python :: 3.11
Classifier: Programming Language :: Python :: 3.12
Requires-Dist: ijson (>=3.3.0,<4.0.0)
Requires-Dist: rapidfuzz (>=3.11.0,<4.0.0)
Requires-Dist: result (>=0.17.0,<0.18.0)
Requires-Dist: rich (>=13.8.1,<14.0.0)
Requires-Dist: textual (>=0.82.0,<0.83.0)
